sphinx_juniper/__init__.py
sphinx_juniper/_static/sphinx-juniper-base.css
sphinx_juniper/_static/sphinx-juniper-callysto.css
sphinx_juniper/_static/sphinx-juniper-material.css
sphinx_juniper/_static/sphinx-juniper-monokai.css
sphinx_juniper/_static/sphinx-juniper-pyiron.css
sphinx_juniper/_static/sphinx-juniper.js
sphinx_juniper-0.0.5.dist-info/LICENSE
sphinx_juniper-0.0.5.dist-info/WHEEL
sphinx_juniper-0.0.5.dist-info/METADATA
sphinx_juniper-0.0.5.dist-info/RECORD
