Metadata-Version: 2.1
Name: sphinx-juniper
Version: 0.0.5
Summary: Convert Jupyter Notebooks into runnable HTML files with Juniper (https://github.com/ines/juniper).
Home-page: https://github.com/ashtonmv/sphinx-juniper
License: MIT
Author: Michael Ashton
Author-email: ashtonmv@gmail.com
Requires-Python: >=3.7,<4.0
Classifier: License :: OSI Approved :: MIT License
Classifier: Programming Language :: Python :: 3
Classifier: Programming Language :: Python :: 3.7
Classifier: Programming Language :: Python :: 3.8
Requires-Dist: sphinx (>=2.0)
Project-URL: Repository, https://github.com/ashtonmv/sphinx-juniper
